pytest_benchmark/__init__.py
pytest_benchmark/__main__.py
pytest_benchmark/cli.py
pytest_benchmark/compat.py
pytest_benchmark/csv.py
pytest_benchmark/fixture.py
pytest_benchmark/histogram.py
pytest_benchmark/hookspec.py
pytest_benchmark/logger.py
pytest_benchmark/plugin.py
pytest_benchmark/session.py
pytest_benchmark/stats.py
pytest_benchmark/table.py
pytest_benchmark/timers.py
pytest_benchmark/utils.py
pytest_benchmark/storage/__init__.py
pytest_benchmark/storage/elasticsearch.py
pytest_benchmark/storage/file.py
pytest_benchmark-5.0.1.dist-info/AUTHORS.rst
pytest_benchmark-5.0.1.dist-info/LICENSE
pytest_benchmark-5.0.1.dist-info/METADATA
pytest_benchmark-5.0.1.dist-info/WHEEL
pytest_benchmark-5.0.1.dist-info/entry_points.txt
pytest_benchmark-5.0.1.dist-info/top_level.txt
pytest_benchmark-5.0.1.dist-info/RECORD
