Metadata-Version: 2.1
Name: pytest-benchmark
Version: 5.0.1
Summary: A ``pytest`` fixture for benchmarking code. It will group the tests into rounds that are calibrated to the chosen timer.
Home-page: https://github.com/ionelmc/pytest-benchmark
Author: Ionel Cristian Mărieș
Author-email: contact@ionelmc.ro
License: BSD-2-Clause
Project-URL: Documentation, https://pytest-benchmark.readthedocs.io/
Project-URL: Changelog, https://pytest-benchmark.readthedocs.io/en/latest/changelog.html
Project-URL: Issue Tracker, https://github.com/ionelmc/pytest-benchmark/issues
Keywords: pytest,benchmark
Classifier: Development Status :: 5 - Production/Stable
Classifier: Framework :: Pytest
Classifier: Intended Audience :: Developers
Classifier: License :: OSI Approved :: BSD License
Classifier: Operating System :: Unix
Classifier: Operating System :: POSIX
Classifier: Operating System :: Microsoft :: Windows
Classifier: Programming Language :: Python
Classifier: Programming Language :: Python :: 3
Classifier: Programming Language :: Python :: 3 :: Only
Classifier: Programming Language :: Python :: 3.8
Classifier: Programming Language :: Python :: 3.9
Classifier: Programming Language :: Python :: 3.10
Classifier: Programming Language :: Python :: 3.11
Classifier: Programming Language :: Python :: 3.12
Classifier: Programming Language :: Python :: Implementation :: CPython
Classifier: Programming Language :: Python :: Implementation :: PyPy
Classifier: Topic :: Software Development :: Testing
Classifier: Topic :: System :: Benchmark
Classifier: Topic :: Utilities
Requires-Python: >=3.9
License-File: LICENSE
License-File: AUTHORS.rst
Requires-Dist: pytest >=3.8
Requires-Dist: py-cpuinfo
Requires-Dist: statistics ; python_version < "3.4"
Requires-Dist: pathlib2 ; python_version < "3.4"
Provides-Extra: aspect
Requires-Dist: aspectlib ; extra == 'aspect'
Provides-Extra: elasticsearch
Requires-Dist: elasticsearch ; extra == 'elasticsearch'
Provides-Extra: histogram
Requires-Dist: pygal ; extra == 'histogram'
Requires-Dist: pygaljs ; extra == 'histogram'
Requires-Dist: setuptools ; extra == 'histogram'
